{
  "name": "Click on created property on edit option",
  "id": "0",
  "type": 3,
  "content": {
    "title": "Click on created property on edit option",
    "specific": [],
    "parameters": [],
    "steps": [
      {
        "commented": false,
        "action": "_click",
        "stepParameters": [
          {
            "paramMode": "code",
            "customValue": "_div(\"ml-64\")"
          }
        ],
        "stepType": "Action",
        "stepCategory": "inbuilt",
        "specific": []
      },
      {
        "commented": false,
        "action": "_click",
        "stepParameters": [
          {
            "paramMode": "code",
            "customValue": "_listItem(\"Edit\")"
          }
        ],
        "stepType": "Action",
        "stepCategory": "inbuilt",
        "specific": []
      }
    ],
    "isSystemKeyword": false
  },
  "enabled": false,
  "parentId": ""
}