{
  "modifiedOn": "2024-05-21T07:46:14.761Z",
  "name": "Enter details to create WA Media Message Template with merge fields $template",
  "id": "46194",
  "type": 3,
  "createdOn": "2024-05-21T07:39:16.668Z",
  "content": {
    "isSystemKeyword": false,
    "title": "Enter details to create WA Media Message Template with merge fields $template",
    "parameters": [
      {
        "parameterId": "template_",
        "entityTypeId": "template",
        "suffix": ""
      }
    ],
    "steps": [
      {
        "commented": true,
        "action": "_click",
        "stepParameters": [
          {
            "isCustomParameter": true,
            "customValue": "_textbox(\"Enter template name\")"
          }
        ],
        "stepType": "Action"
      },
      {
        "commented": false,
        "action": "_wait",
        "stepParameters": [
          {
            "isCustomParameter": true,
            "customValue": "3000"
          }
        ],
        "stepType": "Action"
      },
      {
        "commented": false,
        "isRawScript": true,
        "rawScript": "_focus(_textbox(\"Enter template name\"))"
      },
      {
        "commented": false,
        "action": "_setValue",
        "stepParameters": [
          {
            "isCustomParameter": true,
            "customValue": "_textbox(\"Enter template name\")"
          },
          {
            "parameterId": "template_",
            "attributeId": "attr_01695902827118"
          }
        ],
        "stepType": "Action",
        "visibleCheck": false
      },
      {
        "commented": false,
        "action": "_click",
        "stepParameters": [
          {
            "isCustomParameter": true,
            "customValue": "_fltSemantics(\"Select Template type\")"
          }
        ],
        "stepType": "Action"
      },
      {
        "commented": false,
        "action": "_click",
        "stepParameters": [
          {
            "isCustomParameter": true,
            "customValue": "_fltSemantics(\"Conversation\")"
          }
        ],
        "stepType": "Action"
      },
      {
        "commented": false,
        "action": "_click",
        "stepParameters": [
          {
            "isCustomParameter": true,
            "customValue": "_fltSemantics(\"Select Integration\")"
          }
        ],
        "stepType": "Action"
      },
      {
        "commented": false,
        "action": "_click",
        "stepParameters": [
          {
            "isCustomParameter": true,
            "customValue": "_fltSemantics(\"Conversive\")"
          }
        ],
        "stepType": "Action"
      },
      {
        "commented": false,
        "action": "_wait",
        "stepParameters": [
          {
            "isCustomParameter": true,
            "customValue": "1000"
          }
        ],
        "stepType": "Action"
      },
      {
        "commented": false,
        "action": "_wait",
        "stepParameters": [
          {
            "isCustomParameter": true,
            "customValue": "1000"
          }
        ],
        "stepType": "Action"
      },
      {
        "commented": false,
        "action": "_click",
        "stepParameters": [
          {
            "isCustomParameter": true,
            "customValue": "_fltSemantics(\"Media Message\")"
          }
        ],
        "stepType": "Action"
      },
      {
        "commented": false,
        "action": "_click",
        "stepParameters": [
          {
            "isCustomParameter": true,
            "customValue": "_fltSemantics($template.channelWA)"
          }
        ],
        "stepType": "Action"
      },
      {
        "commented": false,
        "action": "_wait",
        "stepParameters": [
          {
            "isCustomParameter": true,
            "customValue": "3000"
          }
        ],
        "stepType": "Action"
      },
      {
        "commented": false,
        "isRawScript": true,
        "rawScript": "_focus(_textarea(0))"
      },
      {
        "commented": false,
        "action": "_setValue",
        "stepParameters": [
          {
            "isCustomParameter": true,
            "customValue": "_textarea(0)"
          },
          {
            "parameterId": "template_",
            "attributeId": "attr_21695961090879"
          }
        ],
        "stepType": "Action",
        "visibleCheck": false
      },
      {
        "commented": false,
        "action": "_click",
        "stepParameters": [
          {
            "isCustomParameter": true,
            "customValue": "_fltSemantics(\"Select Merge field\")"
          }
        ],
        "stepType": "Action"
      },
      {
        "commented": false,
        "action": "_click",
        "stepParameters": [
          {
            "isCustomParameter": true,
            "customValue": "_fltSemantics($template.mergeField)"
          }
        ],
        "stepType": "Action"
      },
      {
        "commented": false,
        "action": "_click",
        "stepParameters": [
          {
            "isCustomParameter": true,
            "customValue": "_fltSemantics($template.mergeField)"
          }
        ],
        "stepType": "Action"
      },
      {
        "commented": false,
        "action": "_click",
        "stepParameters": [
          {
            "isCustomParameter": true,
            "customValue": "_fltSemantics($template.mergeField1)"
          }
        ],
        "stepType": "Action"
      },
      {
        "commented": false,
        "action": "_click",
        "stepParameters": [
          {
            "isCustomParameter": true,
            "customValue": "_fltSemantics($template.mergeField1)"
          }
        ],
        "stepType": "Action"
      },
      {
        "commented": false,
        "action": "_click",
        "stepParameters": [
          {
            "isCustomParameter": true,
            "customValue": "_fltSemantics($template.mergeField2)"
          }
        ],
        "stepType": "Action"
      },
      {
        "commented": false,
        "action": "_wait",
        "stepParameters": [
          {
            "isCustomParameter": true,
            "customValue": "1500"
          }
        ],
        "stepType": "Action"
      },
      {
        "commented": false,
        "action": "_setFile3",
        "stepParameters": [
          {
            "isCustomParameter": true,
            "customValue": "_fltSemantics(\"/Insert media/\", _rightOf(_fltSemantics($template.mergeField2)))"
          },
          {
            "isCustomParameter": true,
            "customValue": "\"/Users/pranitakolekar/tfc_engine_new/userdata/scripts/Image.jpeg\""
          }
        ],
        "stepType": "Action"
      },
      {
        "commented": false,
        "action": "_wait",
        "stepParameters": [
          {
            "isCustomParameter": true,
            "customValue": "2000"
          }
        ],
        "stepType": "Action"
      },
      {
        "commented": false,
        "action": "_click",
        "stepParameters": [
          {
            "isCustomParameter": true,
            "customValue": "_fltSemantics(\"Is registered Whatsapp template?\")"
          }
        ],
        "stepType": "Action"
      },
      {
        "commented": false,
        "action": "_wait",
        "stepParameters": [
          {
            "isCustomParameter": true,
            "customValue": "3000"
          }
        ],
        "stepType": "Action"
      },
      {
        "commented": false,
        "isRawScript": true,
        "rawScript": "_focus(_textbox(\"/Welcome Text for new/\"))\n"
      },
      {
        "commented": false,
        "action": "_setValue",
        "stepParameters": [
          {
            "isCustomParameter": true,
            "customValue": "_textbox(\"/Welcome Text for new/\")"
          },
          {
            "parameterId": "template_",
            "attributeId": "attr_01695902827118"
          }
        ],
        "stepType": "Action",
        "visibleCheck": false
      },
      {
        "commented": false,
        "action": "_wait",
        "stepParameters": [
          {
            "isCustomParameter": true,
            "customValue": "3000"
          }
        ],
        "stepType": "Action"
      },
      {
        "commented": false,
        "isRawScript": true,
        "rawScript": "_focus(_textbox(\"/whatsapp:hsm/\"))"
      },
      {
        "commented": false,
        "action": "_setValue",
        "stepParameters": [
          {
            "isCustomParameter": true,
            "customValue": "_textbox(\"/whatsapp:hsm/\")"
          },
          {
            "parameterId": "template_",
            "attributeId": "attr_71716214387815"
          }
        ],
        "stepType": "Action",
        "visibleCheck": false
      },
      {
        "commented": false,
        "action": "_click",
        "stepParameters": [
          {
            "isCustomParameter": true,
            "customValue": "_fltSemantics(\"Select Locale\")"
          }
        ],
        "stepType": "Action"
      },
      {
        "commented": false,
        "action": "_wait",
        "stepParameters": [
          {
            "isCustomParameter": true,
            "customValue": "3000"
          }
        ],
        "stepType": "Action"
      },
      {
        "commented": false,
        "isRawScript": true,
        "rawScript": "_focus(_textbox(\"Search\"))"
      },
      {
        "commented": false,
        "action": "_setValue",
        "stepParameters": [
          {
            "isCustomParameter": true,
            "customValue": "_textbox(\"Search\")"
          },
          {
            "isCustomParameter": true,
            "customValue": "\"English\""
          }
        ],
        "stepType": "Action"
      },
      {
        "commented": false,
        "action": "_click",
        "stepParameters": [
          {
            "isCustomParameter": true,
            "customValue": "_fltSemantics(\"English (en)\")"
          }
        ],
        "stepType": "Action"
      },
      {
        "commented": false,
        "action": "_click",
        "stepParameters": [
          {
            "isCustomParameter": true,
            "customValue": "_fltSemantics(\"Save\")"
          }
        ],
        "stepType": "Action"
      },
      {
        "commented": false,
        "action": "_isVisible",
        "stepParameters": [
          {
            "isCustomParameter": true,
            "customValue": "_fltSemantics(\"Template created Successfully\")"
          }
        ],
        "stepType": "Assert",
        "assertType": "Is_True"
      }
    ]
  },
  "enabled": false,
  "parentId": ""
}