{
  "modifiedOn": "2024-08-16T08:45:44.763Z",
  "name": "Go to User management $createchild",
  "id": "58841",
  "type": 3,
  "createdOn": "2024-08-16T07:51:38.728Z",
  "content": {
    "isSystemKeyword": false,
    "title": "Go to User management $createchild",
    "parameters": [
      {
        "parameterId": "createchild_",
        "entityTypeId": "createchild",
        "suffix": ""
      }
    ],
    "steps": [
      {
        "commented": false,
        "action": "_wait",
        "stepParameters": [
          {
            "isCustomParameter": true,
            "customValue": "3000"
          }
        ],
        "stepType": "Action"
      },
      {
        "commented": false,
        "action": "_click",
        "stepParameters": [
          {
            "isCustomParameter": true,
            "customValue": "_div(\"User Management\")"
          }
        ],
        "stepType": "Action"
      }
    ]
  },
  "enabled": false,
  "parentId": ""
}