{
  "modifiedOn": "2024-07-10T08:21:40.306Z",
  "name": "Select the third Field $segmentui",
  "id": "58238",
  "type": 3,
  "createdOn": "2024-07-10T07:58:38.235Z",
  "content": {
    "isSystemKeyword": false,
    "title": "Select the third Field $segmentui",
    "parameters": [
      {
        "parameterId": "segmentui_",
        "entityTypeId": "segmentui",
        "suffix": ""
      }
    ],
    "steps": [
      {
        "commented": false,
        "action": "_click",
        "stepParameters": [
          {
            "isCustomParameter": true,
            "customValue": "_div(\"Select field\")"
          }
        ],
        "stepType": "Action"
      },
      {
        "commented": false,
        "action": "_click",
        "stepParameters": [
          {
            "isCustomParameter": true,
            "customValue": "_div($segmentui.field2, _near(_div(\"Select field\")))"
          }
        ],
        "stepType": "Action"
      },
      {
        "commented": false,
        "action": "_getText",
        "stepParameters": [
          {
            "isCustomParameter": true,
            "customValue": "_div($segmentui.field2)"
          }
        ],
        "stepType": "Assert",
        "assertType": "Equals",
        "secondaryParam": {
          "isCustomParameter": true,
          "customValue": "$segmentui.field2"
        }
      }
    ]
  },
  "enabled": false,
  "parentId": ""
}