{
  "modifiedOn": "2023-12-11T05:34:11.833Z",
  "name": "Buy Now Tab",
  "id": "13816",
  "type": 3,
  "createdOn": "2023-09-06T07:35:56.706Z",
  "content": {
    "isSystemKeyword": false,
    "title": "Buy Now Tab",
    "parameters": [],
    "steps": [
      {
        "commented": false,
        "action": "_click",
        "stepParameters": [
          {
            "isCustomParameter": true,
            "customValue": "_link(\"Buy Now\")"
          }
        ],
        "stepType": "Action"
      },
      {
        "commented": false,
        "action": "_click",
        "stepParameters": [
          {
            "isCustomParameter": true,
            "customValue": "_link(\"Buy SMS\")"
          }
        ],
        "stepType": "Action"
      },
      {
        "commented": false,
        "action": "_navigateTo",
        "stepParameters": [
          {
            "isCustomParameter": true,
            "customValue": "$envURL"
          }
        ],
        "stepType": "Action"
      }
    ]
  },
  "enabled": false,
  "parentId": ""
}