{
  "modifiedOn": "2023-09-22T13:06:31.690Z",
  "name": "Cancel the Inprogress report",
  "id": "14894",
  "type": 3,
  "createdOn": "2023-09-22T11:14:48.116Z",
  "content": {
    "title": "Cancel the Inprogress report",
    "parameters": [],
    "steps": [
      {
        "commented": false,
        "action": "_click",
        "stepParameters": [
          {
            "isCustomParameter": true,
            "customValue": "_button(\"Download Incoming Report\")"
          }
        ],
        "stepType": "Action"
      },
      {
        "commented": false,
        "action": "_click",
        "stepParameters": [
          {
            "isCustomParameter": true,
            "customValue": "_link(\"Download Generated Report\")"
          }
        ],
        "stepType": "Action"
      },
      {
        "commented": false,
        "action": "_click",
        "stepParameters": [
          {
            "isCustomParameter": true,
            "customValue": "_link(\"Cancel\")"
          }
        ],
        "stepType": "Action"
      },
      {
        "commented": true,
        "action": "_isVisible",
        "stepParameters": [
          {
            "isCustomParameter": true,
            "customValue": "_link(\"Cancel\", _near(_cell(\"In progress\")))"
          }
        ],
        "stepType": "Assert",
        "assertType": "Is_False"
      }
    ]
  },
  "enabled": false,
  "parentId": ""
}