{
  "modifiedOn": "2024-08-09T04:09:53.769Z",
  "name": "Send Message from using SMS once guided flow ends $basicinfo for SF",
  "id": "57863",
  "type": 3,
  "createdOn": "2024-06-20T11:55:46.102Z",
  "content": {
    "isSystemKeyword": false,
    "title": "Send Message from using SMS once guided flow ends $basicinfo for SF",
    "parameters": [
      {
        "parameterId": "basicinfo_",
        "entityTypeId": "basicinfo",
        "suffix": ""
      }
    ],
    "steps": [
      {
        "commented": true,
        "stepParameters": [
          {
            "isCustomParameter": true,
            "customValue": "POST"
          },
          {
            "isCustomParameter": true,
            "customValue": "$incomingSMSURLIntelli"
          }
        ],
        "stepType": "REST",
        "isRawScript": true,
        "rawScript": "var $request_TzGizZOLN2 \u003d new RESTRequest();\r\n$request_TzGizZOLN2.setURL($incomingSMSURLIntelli);\r\n$request_TzGizZOLN2.addToQueryString(\"Message\", \"Okay\");\r\n$request_TzGizZOLN2.addToQueryString(\"OriginatorAddress\", $basicinfo.source);\r\n$request_TzGizZOLN2.addToQueryString(\"DestinationAddress\", $SenderIDSMSSF);\r\nvar $response_TzGizZOLN2 \u003d $request_TzGizZOLN2.submit(\"POST\");\r\nvar responseBody \u003d JSON.parse($response_TzGizZOLN2.getBodyAsString());\r\n\t var $responseBodyObj_TzGizZOLN2 \u003d $response_TzGizZOLN2.getBodyAsString();\r\n\tvar responseType \u003d $response_TzGizZOLN2.getHeader(\"Content-Type\");\r\n\tif (responseType.indexOf(\"json\")!\u003d-1) {\r\n\t\t$responseBodyObj_TzGizZOLN2 \u003d JSON.parse($responseBodyObj_TzGizZOLN2);\r\n\t}\r\n\telse if (responseType.indexOf(\"xml\")!\u003d-1) {\r\n\t\t$responseBodyObj_TzGizZOLN2 \u003d $responseBodyObj_TzGizZOLN2.replace(/\u003c\\xml.*?\u003e/g, \u0027\u0027).replace(/\\n/g, \u0027\u0027).replace(/\\r/g, \u0027\u0027);\r\n\t\t$responseBodyObj_TzGizZOLN2 \u003d new XML(undefined);\r\n\t}\r\n\r\n\t//assertions\r\n\r\n",
        "state": {
          "contentType": "json",
          "request": {
            "method": "POST",
            "url": "$incomingSMSURLIntelli",
            "parameters": [
              [
                "Message",
                "Okay"
              ],
              [
                "OriginatorAddress",
                "$basicinfo.source"
              ],
              [
                "DestinationAddress",
                "$SenderIDSMSSF"
              ]
            ],
            "headers": [],
            "authType": "none",
            "body": "",
            "bodyParams": [],
            "isParametrizedBody": false,
            "resetCookies": false
          },
          "assertions": {
            "status": [],
            "header": [],
            "body": []
          },
          "variables": {
            "status": [],
            "header": [],
            "body": []
          },
          "authInfo": {}
        }
      },
      {
        "commented": true,
        "action": "_wait",
        "stepParameters": [
          {
            "isCustomParameter": true,
            "customValue": "5000"
          }
        ],
        "stepType": "Action"
      },
      {
        "commented": false,
        "stepParameters": [
          {
            "isCustomParameter": true,
            "customValue": "POST"
          },
          {
            "isCustomParameter": true,
            "customValue": "$incomingSMSURLTwilio"
          }
        ],
        "stepType": "REST",
        "isRawScript": true,
        "rawScript": "var $request_EMvrThbQfj \u003d new RESTRequest();\r\n$request_EMvrThbQfj.setURL($incomingSMSURLTwilio);\r\n$request_EMvrThbQfj.addToQueryString(\"From\", $basicinfo.source);\r\n$request_EMvrThbQfj.addToQueryString(\"To\", $SenderIDSMSSF);\r\n$request_EMvrThbQfj.addToQueryString(\"Body\", \"Okay\");\r\n$request_EMvrThbQfj.addToQueryString(\"SmsSid\", \"3455656676\");\r\nvar $response_EMvrThbQfj \u003d $request_EMvrThbQfj.submit(\"POST\");\r\n\t var $responseBodyObj_EMvrThbQfj \u003d $response_EMvrThbQfj.getBodyAsString();\r\n\tvar responseType \u003d $response_EMvrThbQfj.getHeader(\"Content-Type\");\r\n\tif (responseType.indexOf(\"json\")!\u003d-1) {\r\n\t\t$responseBodyObj_EMvrThbQfj \u003d JSON.parse($responseBodyObj_EMvrThbQfj);\r\n\t}\r\n\telse if (responseType.indexOf(\"xml\")!\u003d-1) {\r\n\t\t$responseBodyObj_EMvrThbQfj \u003d $responseBodyObj_EMvrThbQfj.replace(/\u003c\\xml.*?\u003e/g, \u0027\u0027).replace(/\\n/g, \u0027\u0027).replace(/\\r/g, \u0027\u0027);\r\n\t\t$responseBodyObj_EMvrThbQfj \u003d new XML(undefined);\r\n\t}\r\n\r\n\t//assertions\r\n\r\n",
        "state": {
          "contentType": "html",
          "request": {
            "method": "POST",
            "url": "$incomingSMSURLTwilio",
            "parameters": [
              [
                "From",
                "$basicinfo.source"
              ],
              [
                "To",
                "$SenderIDSMSSF"
              ],
              [
                "Body",
                "Okay"
              ],
              [
                "SmsSid",
                "3455656676"
              ]
            ],
            "headers": [],
            "authType": "none",
            "body": "",
            "bodyParams": [],
            "isParametrizedBody": false,
            "resetCookies": false
          },
          "assertions": {
            "status": [],
            "header": [],
            "body": []
          },
          "variables": {
            "status": [],
            "header": [],
            "body": []
          },
          "authInfo": {}
        }
      },
      {
        "commented": false,
        "action": "_wait",
        "stepParameters": [
          {
            "isCustomParameter": true,
            "customValue": "5000"
          }
        ],
        "stepType": "Action"
      }
    ]
  },
  "enabled": false,
  "parentId": ""
}