{
  "description": "",
  "title": "BeConversive Portal",
  "content": {
    "isCustomFunctionsFromScriptsDir": false,
    "projectSuiteInfo": [],
    "filters": {
      "flt_trial_signup_saas_true_0": {
        "combo": {
          "$trial_signup._saas": true
        },
        "id": "flt_trial_signup_saas_true_0"
      }
    },
    "executionOrder": [
      "10DLC",
      "Account Activity",
      "AI in Automation",
      "Audience Manager - Manage Property",
      "Audience Manager Be Conversive",
      "Audience Manager Campaign Flow",
      "Audience Segment",
      "Be conversive",
      "beconversiveConsent managment",
      "BeconversiveSanity_Ajay",
      "Business Hours",
      "BYOP Integration",
      "Campaign",
      "Converse Desk",
      "Conversive 10dlc new UI",
      "Conversive Analytics Dashboard",
      "Conversive Associated Accounts",
      "Conversive Business Hour",
      "Conversive Button Improvements",
      "Conversive Button SMS",
      "Conversive button Web Channel",
      "Conversive Button Whats App",
      "Conversive Contact",
      "Conversive Converse Desk",
      "Conversive Email Template",
      "Conversive Feature Request",
      "Conversive Help",
      "Conversive Integration",
      "Conversive OPS for Plans",
      "Conversive Overview",
      "Conversive Performance Testing",
      "Conversive Sanity Suite",
      "Conversive Sender Id Allocation",
      "Conversive SMS History",
      "Conversive Subscriber Access",
      "Conversive Template",
      "Conversive URL SNT",
      "Conversive Wallet",
      "Custom Gpt",
      "Guided Flows",
      "HIPPA",
      "Intiating New conversation with SF and ZOHO from desk",
      "KT Demo",
      "Lead Capture for Audience Manager",
      "Master - SAAS Customer Portal",
      "New Licnese Feature",
      "new Master",
      "Pawan_sanity",
      "Plan Expiry Banners",
      "Saas Customer Portal ",
      "Salesforce",
      "Sanity Suite Be Conversive",
      "Send SMS Validation",
      "Session Inactivity",
      "Shared Inbox SaaS",
      "Show only CRMs while sending messages",
      "Smoke",
      "SMS Services",
      "Student Inquiries Assistance",
      "Student Inquiries Assistance SMS",
      "Template Hubspot merge field",
      "Test",
      "Trial Signup  Flows",
      "Trigger Conversational Flow On Hubspot",
      "Usecases Guided Flow ",
      "User Management",
      "User Permission",
      "VM-SMOKE",
      "Zoho and Zoho Bigin Campaign List View",
      "Zoho Campaign",
      "ZOHO Execution",
      "Shraddha Sanity",
      "Do not show invalid template on beconversive desk"
    ]
  }
}