{
  "modifiedOn": "2024-08-16T13:29:41.031Z",
  "name": "Verify the Added Property on UI $property",
  "id": "58858",
  "type": 3,
  "createdOn": "2024-08-16T11:34:51.270Z",
  "content": {
    "isSystemKeyword": false,
    "title": "Verify the Added Property on UI $property",
    "parameters": [
      {
        "parameterId": "property_",
        "entityTypeId": "property",
        "suffix": ""
      }
    ],
    "steps": [
      {
        "commented": false,
        "action": "_wait",
        "stepParameters": [
          {
            "isCustomParameter": true,
            "customValue": "3000"
          }
        ],
        "stepType": "Action"
      },
      {
        "commented": false,
        "action": "_getText",
        "stepParameters": [
          {
            "isCustomParameter": true,
            "customValue": "_paragraph(\"/Showing .* contact properties/\")"
          }
        ],
        "stepType": "Store",
        "secondaryParam": {
          "isCustomParameter": true,
          "customValue": "$newNumberOfProperty"
        }
      },
      {
        "commented": false,
        "isRawScript": true,
        "rawScript": "var $trimmedText \u003d $newNumberOfProperty.trim();\n\n$newNumber \u003d $trimmedText.match(/\\d+/);\n\nvar $inc\u003d1;\nvar $fCount\u003dNumber($number) + $inc ;\n_log($fCount);\n\n_assertEqual($fCount, $newNumber)"
      },
      {
        "commented": false,
        "action": "_getText",
        "stepParameters": [
          {
            "isCustomParameter": true,
            "customValue": "_paragraph($property.propertyName)"
          }
        ],
        "stepType": "Assert",
        "assertType": "Equals",
        "secondaryParam": {
          "parameterId": "property_",
          "attributeId": "attr_01723806477739"
        },
        "visibleCheck": false
      }
    ]
  },
  "enabled": false,
  "parentId": ""
}