{
  "name": "Verify error msg",
  "id": "0",
  "type": 3,
  "content": {
    "isSystemKeyword": false,
    "title": "Verify error msg",
    "specific": [],
    "parameters": [],
    "steps": [
      {
        "commented": false,
        "action": "_getText",
        "stepParameters": [
          {
            "paramMode": "code",
            "customValue": "_div(\"alert alert-danger alert-dismissible\")"
          }
        ],
        "stepCategory": "inbuilt",
        "stepType": "Assert",
        "assertType": "Contains",
        "secondaryParam": {
          "paramMode": "code",
          "customValue": "\"Warning: Coupon is either invalid, expired or reached its usage limit!\""
        },
        "specific": []
      }
    ]
  },
  "enabled": false,
  "parentId": ""
}