{
  "modifiedOn": "2024-09-05T10:15:12.210Z",
  "name": "create $newconversivebutton with Form and Consent Enable and Change the Consent message",
  "id": "59012",
  "type": 3,
  "createdOn": "2024-09-03T07:38:24.939Z",
  "content": {
    "isSystemKeyword": false,
    "title": "create $newconversivebutton with Form and Consent Enable and Change the Consent message",
    "parameters": [
      {
        "parameterId": "newconversivebutton_",
        "entityTypeId": "newconversivebutton",
        "suffix": ""
      }
    ],
    "steps": [
      {
        "commented": false,
        "action": "_click",
        "stepParameters": [
          {
            "isCustomParameter": true,
            "customValue": "_submit(\"update_btn\")"
          }
        ],
        "stepType": "Action"
      },
      {
        "commented": false,
        "action": "_setValue",
        "stepParameters": [
          {
            "parameterId": "newconversivebutton_",
            "attributeId": "attr_01693801371237",
            "accessorId": "acc0"
          },
          {
            "parameterId": "newconversivebutton_",
            "attributeId": "attr_01693801371237"
          }
        ],
        "stepType": "Action",
        "visibleCheck": false
      },
      {
        "commented": false,
        "action": "_click",
        "stepParameters": [
          {
            "isCustomParameter": true,
            "customValue": "_submit(0, _near(_textbox(0)))"
          }
        ],
        "stepType": "Action"
      },
      {
        "commented": false,
        "action": "_click",
        "stepParameters": [
          {
            "isCustomParameter": true,
            "customValue": "_div(\"SMS\")"
          }
        ],
        "stepType": "Action"
      },
      {
        "commented": false,
        "action": "_click",
        "stepParameters": [
          {
            "isCustomParameter": true,
            "customValue": "_div(\"Web Chat\")"
          }
        ],
        "stepType": "Action"
      },
      {
        "commented": false,
        "action": "_getText",
        "stepParameters": [
          {
            "isCustomParameter": true,
            "customValue": "_div(\"/Web Chat/\")"
          }
        ],
        "stepType": "Assert",
        "assertType": "Equals",
        "secondaryParam": {
          "isCustomParameter": true,
          "customValue": "\"Web Chat\""
        }
      },
      {
        "commented": false,
        "action": "_getText",
        "stepParameters": [
          {
            "isCustomParameter": true,
            "customValue": "_label(\"Phone Number\", _near(_div(\"/Web Chat/\")))"
          }
        ],
        "stepType": "Assert",
        "assertType": "Equals",
        "secondaryParam": {
          "isCustomParameter": true,
          "customValue": "\"Phone Number\""
        }
      },
      {
        "commented": false,
        "action": "_getText",
        "stepParameters": [
          {
            "isCustomParameter": true,
            "customValue": "_div(\" css-hlgwow\")"
          }
        ],
        "stepType": "Assert",
        "assertType": "Contains",
        "secondaryParam": {
          "isCustomParameter": true,
          "customValue": "\"WEB-DEMO-\""
        }
      },
      {
        "commented": false,
        "action": "_isVisible",
        "stepParameters": [
          {
            "isCustomParameter": true,
            "customValue": "_div(\"form-rectangle\")"
          }
        ],
        "stepType": "Assert",
        "assertType": "Is_True"
      },
      {
        "commented": false,
        "action": "_getText",
        "stepParameters": [
          {
            "isCustomParameter": true,
            "customValue": "_div(\"Contact Information Form\")"
          }
        ],
        "stepType": "Assert",
        "assertType": "Equals",
        "secondaryParam": {
          "isCustomParameter": true,
          "customValue": "\"Contact Information Form\""
        }
      },
      {
        "commented": false,
        "action": "_isChecked",
        "stepParameters": [
          {
            "isCustomParameter": true,
            "customValue": "_checkbox(0,_near(_label(\"switch\")))"
          }
        ],
        "stepType": "Assert",
        "assertType": "Is_True"
      },
      {
        "commented": false,
        "action": "_getText",
        "stepParameters": [
          {
            "isCustomParameter": true,
            "customValue": "_paragraph(\"Enable the default form interface in webchat to capture essential contact details, including first name, last name, email, and phone number.\")"
          }
        ],
        "stepType": "Assert",
        "assertType": "Equals",
        "secondaryParam": {
          "isCustomParameter": true,
          "customValue": "\"Enable the default form interface in webchat to capture essential contact details, including first name, last name, email, and phone number.\""
        }
      },
      {
        "commented": false,
        "action": "_isChecked",
        "stepParameters": [
          {
            "isCustomParameter": true,
            "customValue": "_checkbox(0,_in(_div(\"Create and store the consent upon form completion\")))"
          }
        ],
        "stepType": "Assert",
        "assertType": "Is_True"
      },
      {
        "commented": false,
        "action": "_getText",
        "stepParameters": [
          {
            "isCustomParameter": true,
            "customValue": "_label(\"Create and store the consent upon form completion\")"
          }
        ],
        "stepType": "Assert",
        "assertType": "Equals",
        "secondaryParam": {
          "isCustomParameter": true,
          "customValue": "\"Create and store the consent upon form completion\""
        }
      },
      {
        "commented": false,
        "action": "_getText",
        "stepParameters": [
          {
            "isCustomParameter": true,
            "customValue": "_div(\"public-DraftStyleDefault-block public-DraftStyleDefault-ltr\")"
          }
        ],
        "stepType": "Assert",
        "assertType": "Equals",
        "secondaryParam": {
          "isCustomParameter": true,
          "customValue": "\"By starting the chat, you consent to receive communication across various channels from us\""
        }
      },
      {
        "commented": false,
        "action": "_isVisible",
        "stepParameters": [
          {
            "isCustomParameter": true,
            "customValue": "_span(\"link\")"
          }
        ],
        "stepType": "Assert",
        "assertType": "Is_True"
      },
      {
        "commented": false,
        "isRawScript": true,
        "rawScript": "_wait(2000)\n\nif($machine \u003d\u003d \"macOS\"){\n_wait(1000)\nvar $robot \u003d new java.awt.Robot();\n$robot.keyPress(java.awt.event.KeyEvent.VK_META);\n$robot.keyPress(java.awt.event.KeyEvent.VK_CONTROL);\n$robot.keyPress(java.awt.event.KeyEvent.VK_F);\n$robot.keyRelease(java.awt.event.KeyEvent.VK_F);\n$robot.keyRelease(java.awt.event.KeyEvent.VK_CONTROL);\n$robot.keyRelease(java.awt.event.KeyEvent.VK_META);\n}\nif($machine \u003d\u003d \"windows\" || $machine \u003d\u003d \"chromeOS\"){\n_typeKeyCodeNative(java.awt.event.KeyEvent.VK_F11);\n}\n\n\n_focus(_span(0,_under(_div(\"Contact Information Form\"),25)));\n$a \u003d _getText(_span(0,_under(_div(\"Contact Information Form\"),25)))\n_selectTextRange(_span(0,_under(_div(\"Contact Information Form\"),25)),$a)\n_typeKeyCodeNative(java.awt.event.KeyEvent.VK_BACK_SPACE);\n_setValue(_span(0,_under(_div(\"Contact Information Form\"),25)),$newconversivebutton.consentMessage);\n\n_wait(2000)\n\n\n\nif($machine \u003d\u003d \"macOS\"){\n_wait(1000)\nvar $robot \u003d new java.awt.Robot();\n$robot.keyPress(java.awt.event.KeyEvent.VK_META);\n$robot.keyPress(java.awt.event.KeyEvent.VK_CONTROL);\n$robot.keyPress(java.awt.event.KeyEvent.VK_F);\n$robot.keyRelease(java.awt.event.KeyEvent.VK_F);\n$robot.keyRelease(java.awt.event.KeyEvent.VK_CONTROL);\n$robot.keyRelease(java.awt.event.KeyEvent.VK_META);\n}\nif($machine \u003d\u003d \"windows\" || $machine \u003d\u003d \"chromeOS\"){\n_typeKeyCodeNative(java.awt.event.KeyEvent.VK_F11);\n}\n\n"
      },
      {
        "commented": false,
        "action": "_setValue",
        "stepParameters": [
          {
            "isCustomParameter": true,
            "customValue": "_textbox(\"domain\")"
          },
          {
            "isCustomParameter": true,
            "customValue": "$testURL"
          }
        ],
        "stepType": "Action"
      },
      {
        "commented": false,
        "action": "_click",
        "stepParameters": [
          {
            "isCustomParameter": true,
            "customValue": "_submit(\"Generate Script\")"
          }
        ],
        "stepType": "Action"
      },
      {
        "commented": false,
        "action": "_getText",
        "stepParameters": [
          {
            "isCustomParameter": true,
            "customValue": "_span(\"Your script has been successfully generated! Follow the provided instructions to embed it on your website for enhanced user engagement.\")"
          }
        ],
        "stepType": "Assert",
        "assertType": "Equals",
        "secondaryParam": {
          "isCustomParameter": true,
          "customValue": "\"Your script has been successfully generated! Follow the provided instructions to embed it on your website for enhanced user engagement.\""
        }
      },
      {
        "commented": false,
        "action": "_getText",
        "stepParameters": [
          {
            "isCustomParameter": true,
            "customValue": "_submit(\"Copy code\")"
          }
        ],
        "stepType": "Assert",
        "assertType": "Equals",
        "secondaryParam": {
          "isCustomParameter": true,
          "customValue": "\"Copy code\""
        }
      },
      {
        "commented": false,
        "action": "_getText",
        "stepParameters": [
          {
            "isCustomParameter": true,
            "customValue": "_span(\"Paste the script inside the \u003chead\u003e OR \u003cbody\u003e tag on every page you want the Conversive widget to appear.\")"
          }
        ],
        "stepType": "Assert",
        "assertType": "Equals",
        "secondaryParam": {
          "isCustomParameter": true,
          "customValue": "\"Paste the script inside the \u003chead\u003e OR \u003cbody\u003e tag on every page you want the Conversive widget to appear.\""
        }
      },
      {
        "commented": false,
        "action": "_getText",
        "stepParameters": [
          {
            "isCustomParameter": true,
            "customValue": "_div(\"Configuration changes will automatically reflect once the script is embedded on your website.\")"
          }
        ],
        "stepType": "Assert",
        "assertType": "Equals",
        "secondaryParam": {
          "isCustomParameter": true,
          "customValue": "\"Configuration changes will automatically reflect once the script is embedded on your website.\""
        }
      },
      {
        "commented": false,
        "action": "_getText",
        "stepParameters": [
          {
            "isCustomParameter": true,
            "customValue": "_submit(\"Copy Script\")"
          }
        ],
        "stepType": "Assert",
        "assertType": "Equals",
        "secondaryParam": {
          "isCustomParameter": true,
          "customValue": "\"Copy Script\""
        }
      },
      {
        "commented": false,
        "action": "_getText",
        "stepParameters": [
          {
            "isCustomParameter": true,
            "customValue": "_paragraph(\"Configuration changes will automatically reflect once the script is embedded on your website.\")"
          }
        ],
        "stepType": "Assert",
        "assertType": "Equals",
        "secondaryParam": {
          "isCustomParameter": true,
          "customValue": "\"Configuration changes will automatically reflect once the script is embedded on your website.\""
        }
      },
      {
        "commented": false,
        "action": "_getText",
        "stepParameters": [
          {
            "isCustomParameter": true,
            "customValue": "_div(\"public-DraftStyleDefault-block public-DraftStyleDefault-ltr\")"
          }
        ],
        "stepType": "Store",
        "secondaryParam": {
          "isCustomParameter": true,
          "customValue": "$updatedConsentMessage"
        }
      }
    ]
  },
  "enabled": false,
  "parentId": ""
}